tucavoc/__init__.py
tucavoc/__main__.py
tucavoc/abstract_uncertainty.py
tucavoc/calculations.py
tucavoc/equations.py
tucavoc/flags.py
tucavoc/parameters.py
tucavoc/plots.py
tucavoc/settings.py
tucavoc/station.py
tucavoc/tex.py
tucavoc/uncertainties.py
tucavoc/utils.py
tucavoc/additional_data/__init__.py
tucavoc/additional_data/empa.py
tucavoc/additional_data/station.py
tucavoc/additional_data/widget.py
tucavoc/exports/__init__.py
tucavoc/exports/ebas_genfile.py
tucavoc/exports/ebas_test.py
tucavoc/exports/empa_qa_tools.py
tucavoc/exports/excel.py
tucavoc/exports/test_exports.py
tucavoc/exports/utils.py
tucavoc/testing/datasets.py
tucavoc/widgets/__init__.py
tucavoc/widgets/__main__.py
tucavoc/widgets/main.py
tucavoc/widgets/parameters.py
tucavoc/widgets/qsettings_selector.py
tucavoc/widgets/station.py
tucavoc/widgets/style_sheet.qss
tucavoc/widgets/substances.py
tucavoc/widgets/uncertainties.py
tucavoc/widgets/utils.py
tucavoc-0.1.3.dist-info/METADATA
tucavoc-0.1.3.dist-info/WHEEL
tucavoc-0.1.3.dist-info/RECORD
