Metadata-Version: 2.4
Name: tucavoc
Version: 0.1.3
Summary: Application to calculate concentration and uncertainties of chromatography measurements
Author-email: Lionel Constantin <lionel.constantin@empa.ch>, Stefan Reimann <Stefan.Reimann@empa.ch>
License-Expression: MIT
Keywords: area,calculation,chromatography,concentration,measurements,uncertainties
Classifier: Programming Language :: Python :: 3
Requires-Python: >=3.10
Requires-Dist: avoca
Requires-Dist: numpy
Requires-Dist: openpyxl
Requires-Dist: pandas
Requires-Dist: tzdata
Provides-Extra: dev
Requires-Dist: black; extra == 'dev'
Provides-Extra: doc
Requires-Dist: enum-tools; extra == 'doc'
Requires-Dist: furo; extra == 'doc'
Requires-Dist: sphinx; extra == 'doc'
Requires-Dist: sphinx-toolbox; extra == 'doc'
Provides-Extra: gui
Requires-Dist: matplotlib; extra == 'gui'
Requires-Dist: pyside6; extra == 'gui'
